test/__init__.py
test/test_clients.py
test/test_e2e.py
uvs_training_sdk/__init__.py
uvs_training_sdk/clients/__init__.py
uvs_training_sdk/clients/client.py
uvs_training_sdk/clients/common.py
uvs_training_sdk/clients/dataset_client.py
uvs_training_sdk/clients/evaluation_client.py
uvs_training_sdk/clients/prediction_client.py
uvs_training_sdk/clients/training_client.py
uvs_training_sdk/models/__init__.py
uvs_training_sdk/models/common.py
uvs_training_sdk/models/dataset_models.py
uvs_training_sdk/models/evaluation_models.py
uvs_training_sdk/models/training_models.py
uvs_training_sdk-0.0.8.dist-info/LICENSE
uvs_training_sdk-0.0.8.dist-info/METADATA
uvs_training_sdk-0.0.8.dist-info/WHEEL
uvs_training_sdk-0.0.8.dist-info/top_level.txt
uvs_training_sdk-0.0.8.dist-info/RECORD
