Metadata-Version: 2.1
Name: uvs-training-sdk
Version: 0.0.8
Summary: A sample python SDK for training and prediction with Unified Vision Service.
Home-page: 
Author: Ping Jin
License: MIT
Keywords: vision datasets classification detection
Classifier: Development Status :: 4 - Beta
Classifier: Intended Audience :: Developers
Classifier: License :: OSI Approved :: MIT License
Classifier: Programming Language :: Python :: 3.7
Classifier: Programming Language :: Python :: 3.8
Classifier: Programming Language :: Python :: 3.9
Classifier: Programming Language :: Python :: 3.10
Requires-Python: >=3.7
License-File: LICENSE
Requires-Dist: requests
Requires-Dist: tqdm
